{
	"id": "4f390d36-cb26-452c-9fc4-0f11e776ee3f",
	"name": "Batch21",
	"values": [
		{
			"key": "base_url",
			"value": "https://restful-booker.herokuapp.com\n",
			"type": "default",
			"enabled": true
		},
		{
			"key": "id",
			"value": "",
			"type": "any",
			"enabled": true
		},
		{
			"key": "accessToken",
			"value": "",
			"type": "any",
			"enabled": true
		},
		{
			"key": "firstName",
			"value": "",
			"type": "any",
			"enabled": true
		},
		{
			"key": "lastName",
			"value": "",
			"type": "any",
			"enabled": true
		},
		{
			"key": "checkin",
			"value": "",
			"type": "any",
			"enabled": true
		}
	],
	"_postman_variable_scope": "environment",
	"_postman_exported_at": "2023-11-15T13:57:50.407Z",
	"_postman_exported_using": "Postman/10.20.0-231018-1251"
}